{"name":"Projeto Business Intelligence IFNMG","tagline":"Portal de Business Intelligence do IFNMG","body":"### Bem vindo!\r\nBem vindos ao projeto Portal de Business Intelligence do IFNMG! Aqui nossa equipe trabalha para construir e manter as informações sempre confiáveis e atualizadas!\r\n\r\nEsse é um projeto de código aberto que utiliza ferramentas de código aberto! \r\n\r\nEssa é uma pesquisa financiada pelo [Instituto Federal de Educação, Ciência e Tecnologia do Norte de Minas Gerais - IFNMG](http://www.ifnmg.edu.br/) e executada por professores e alunos do curso de [Tecnologia em Análise e Desenvolvimento - TADS](http://www.ifnmg.edu.br/) do [Campus Januária](http://www.ifnmg.edu.br/). O projeto da pesquisa pode ser acessado [aqui](https://github.com/petroniocandido/IFNMG_BI/blob/master/Documentacao/Projeto%20de%20Pesquisa%20-%20Completo.pdf).\r\n\r\nNosso objetivo é contribuir para a democratização no acesso às informações quantitativas do IFNMG e auxiliar no planejamento e tomada de decisões nos níveis estratégico, tático e operacional.\r\n\r\n\r\n### Equipe de Projeto\r\n\r\n* **Prof. Me. Petrônio Cândido de Lima e Silva** - (petronio.candido@ifnmg.edu.br)\r\n  * Coordenador e professor do curso de TADS do IFNMG Campus Januária.\r\n  * Responsável pela aquisição de dados no IFNMG e unificação dos DataMarts no Data Warehouse\r\n* **Rodrigo Martins** - (rodrigomartins.tads@gmail.com)\r\n  * Bolsista PIBIC, aluno do 5º período do curso de TADS do IFNMG Campus Januária.\r\n  * Responsável pelo data mart Biblioteca\r\n* **Maike Jordan** - (maikejrs@hotmail.com)\r\n  * Orientando de TCC, aluno do 5º período do curso de TADS do IFNMG Campus Januária\r\n  * Responsável pelo data mart Acadêmico\r\n\r\n### Páginas do Projeto\r\n* [Pendências e Tarefas](https://github.com/petroniocandido/IFNMG_BI/issues)\r\n* [Normas e Padrões](https://github.com/petroniocandido/IFNMG_BI/wiki/_pages)\r\n* [Código Fonte](https://github.com/petroniocandido/IFNMG_BI)\r\n\r\n### Páginas Externas\r\n* [IFNMG](http://www.ifnmg.edu.br)\r\n* [Pentaho Community Edition](http://community.pentaho.com/)\r\n* [MySql](http://www.mysql.com/)\r\n* [Dados Abertos do Governo Federal](http://dados.gov.br)\r\n* [Guia de Dados Abertos](http://opendatahandbook.org/pt_BR/)","google":"","note":"Don't delete this file! It's used internally to help with page regeneration."}